MANIFEST.in
README.md
setup.cfg
setup.py
airlib.egg-info/PKG-INFO
airlib.egg-info/SOURCES.txt
airlib.egg-info/dependency_links.txt
airlib.egg-info/top_level.txt
net/__init__.py
net/hi.py