Metadata-Version: 1.0
Name: airlib
Version: 1.0.0
Summary: A airlib sample Python project
Home-page: UNKNOWN
Author: air lee
Author-email: UNKNOWN
License: UNKNOWN
Platform: any
